odoo8_addon_hr_expense_analytic_plans-8.0.1.0.0.99.dev9-nspkg.pth
odoo_addons/hr_expense_analytic_plans/README.rst
odoo_addons/hr_expense_analytic_plans/__init__.py
odoo_addons/hr_expense_analytic_plans/__openerp__.py
odoo_addons/hr_expense_analytic_plans/i18n/de.po
odoo_addons/hr_expense_analytic_plans/i18n/es.po
odoo_addons/hr_expense_analytic_plans/i18n/fi.po
odoo_addons/hr_expense_analytic_plans/i18n/fr.po
odoo_addons/hr_expense_analytic_plans/i18n/hr_expense_analytic_plans.pot
odoo_addons/hr_expense_analytic_plans/i18n/nl.po
odoo_addons/hr_expense_analytic_plans/i18n/pt_BR.po
odoo_addons/hr_expense_analytic_plans/i18n/sl.po
odoo_addons/hr_expense_analytic_plans/models/__init__.py
odoo_addons/hr_expense_analytic_plans/models/hr_expense_expense.py
odoo_addons/hr_expense_analytic_plans/models/hr_expense_line.py
odoo_addons/hr_expense_analytic_plans/static/description/icon.png
odoo_addons/hr_expense_analytic_plans/tests/__init__.py
odoo_addons/hr_expense_analytic_plans/tests/test_hr_expense_analytic_plans.py
odoo_addons/hr_expense_analytic_plans/views/hr_expense.xml
odoo_addons/hr_expense_analytic_plans/views/hr_expense_line.xml
odoo8_addon_hr_expense_analytic_plans-8.0.1.0.0.99.dev9.dist-info/METADATA
odoo8_addon_hr_expense_analytic_plans-8.0.1.0.0.99.dev9.dist-info/WHEEL
odoo8_addon_hr_expense_analytic_plans-8.0.1.0.0.99.dev9.dist-info/namespace_packages.txt
odoo8_addon_hr_expense_analytic_plans-8.0.1.0.0.99.dev9.dist-info/top_level.txt
odoo8_addon_hr_expense_analytic_plans-8.0.1.0.0.99.dev9.dist-info/RECORD
